{
  "$schema": "https://docs.renovatebot.com/renovate-schema.json",
  "extends": ["config:recommended", ":dependencyDashboard", ":semanticCommits", "schedule:weekly"],
  "rangeStrategy": "bump",
  "lockFileMaintenance": { "enabled": true, "schedule": ["before 5am on monday"] },
  "packageRules": [
    {
      "description": "Atomic kalpam release: group the @kalpam/* npm bumps with the rozomod/kalpam git-tag refs (copier + lefthook)",
      "matchPackageNames": ["@kalpam/**", "rozomod/kalpam"],
      "groupName": "kalpam release",
      "automerge": true,
      "automergeType": "pr",
      "minimumReleaseAge": "3 days"
    },
    { "description": "Never auto-merge majors", "matchUpdateTypes": ["major"], "automerge": false },
    {
      "description": "Pin GitHub Actions to digests",
      "matchManagers": ["github-actions"],
      "pinDigests": true
    }
  ],
  "copier": { "enabled": true, "versioning": "semver" },
  "customManagers": [
    {
      "customType": "regex",
      "description": "Bump the lefthook remote ref to the latest rozomod/kalpam tag",
      "managerFilePatterns": ["/(^|/)lefthook\\.ya?ml$/"],
      "matchStrings": [
        "git_url:\\s*https://github\\.com/(?<depName>rozomod/kalpam)[\\s\\S]*?ref:\\s*(?<currentValue>v[0-9][0-9.]*)"
      ],
      "datasourceTemplate": "github-tags"
    },
    {
      "customType": "regex",
      "description": "Bump Cloudflare wrangler compatibility_date to the latest workerd release date",
      "managerFilePatterns": ["/(^|/)wrangler\\.jsonc?$/"],
      "matchStrings": ["\"compatibility_date\"\\s*:\\s*\"(?<currentValue>\\d{4}-\\d{2}-\\d{2})\""],
      "depNameTemplate": "cloudflare/workerd",
      "packageNameTemplate": "cloudflare/workerd",
      "datasourceTemplate": "github-releases",
      "extractVersionTemplate": "^v1\\.(?<version>\\d{8})\\.\\d+$",
      "versioningTemplate": "regex:^v?1?\\.?(?<major>\\d{4})-?(?<minor>\\d{2})-?(?<patch>\\d{2})(\\.\\d+)?$"
    }
  ]
}
